README.rst
setup.cfg
setup.py
django_static_lor.egg-info/PKG-INFO
django_static_lor.egg-info/SOURCES.txt
django_static_lor.egg-info/dependency_links.txt
django_static_lor.egg-info/not-zip-safe
django_static_lor.egg-info/pbr.json
django_static_lor.egg-info/requires.txt
django_static_lor.egg-info/top_level.txt
lor/__init__.py
lor/admin.py
lor/models.py
lor/settings.py
lor/storage.py
lor/views.py
lor/management/__init__.py
lor/management/commands/__init__.py
lor/management/commands/wget.py
lor/migrations/__init__.py
lor/templatetags/__init__.py
lor/templatetags/lor.py
tests/__init__.py
tests/runtests.py
tests/testapp/__init__.py
tests/testapp/admin.py
tests/testapp/models.py
tests/testapp/tests.py
tests/testapp/views.py
tests/testapp/migrations/__init__.py